odoo/addons/connector_typesense/README.rst
odoo/addons/connector_typesense/__init__.py
odoo/addons/connector_typesense/__manifest__.py
odoo/addons/connector_typesense/demo/backend_demo.xml
odoo/addons/connector_typesense/i18n/connector_typesense.pot
odoo/addons/connector_typesense/i18n/it.po
odoo/addons/connector_typesense/models/__init__.py
odoo/addons/connector_typesense/models/se_backend.py
odoo/addons/connector_typesense/readme/CONFIGURE.rst
odoo/addons/connector_typesense/readme/CONTRIBUTORS.rst
odoo/addons/connector_typesense/readme/DESCRIPTION.rst
odoo/addons/connector_typesense/readme/INSTALL.rst
odoo/addons/connector_typesense/readme/USAGE.rst
odoo/addons/connector_typesense/static/description/icon.png
odoo/addons/connector_typesense/static/description/index.html
odoo/addons/connector_typesense/tests/__init__.py
odoo/addons/connector_typesense/tests/docker-compose.typesense.example.yml
odoo/addons/connector_typesense/tests/test_connector_typesense.py
odoo/addons/connector_typesense/tests/cassettes/TestConnectorTypesense.test_index_adapter_delete.yaml
odoo/addons/connector_typesense/tests/cassettes/TestConnectorTypesense.test_index_adapter_delete_nonexisting_documents.yaml
odoo/addons/connector_typesense/tests/cassettes/TestConnectorTypesense.test_index_adapter_index_and_iter.yaml
odoo/addons/connector_typesense/tests/cassettes/TestConnectorTypesense.test_index_adapter_reindex.yaml
odoo/addons/connector_typesense/tests/cassettes/TestConnectorTypesense.test_update_schema.yaml
odoo/addons/connector_typesense/tools/__init__.py
odoo/addons/connector_typesense/tools/adapter.py
odoo/addons/connector_typesense/views/ts_backend.xml
odoo_addon_connector_typesense-16.0.1.0.0.5.dist-info/METADATA
odoo_addon_connector_typesense-16.0.1.0.0.5.dist-info/WHEEL
odoo_addon_connector_typesense-16.0.1.0.0.5.dist-info/top_level.txt
odoo_addon_connector_typesense-16.0.1.0.0.5.dist-info/RECORD
