Metadata-Version: 2.1
Name: odoo-addon-connector_typesense
Version: 16.0.1.0.0.5
Summary: Connector For Typesense Search Engine
Home-page: https://github.com/OCA/search-engine
Author: Derico, Kencove, Odoo Community Association (OCA)
Author-email: support@odoo-community.org
License: AGPL-3
Classifier: Programming Language :: Python
Classifier: Framework :: Odoo
Classifier: Framework :: Odoo :: 16.0
Classifier: License :: OSI Approved :: GNU Affero General Public License v3
Requires-Python: >=3.10
Requires-Dist: odoo-addon-connector-search-engine<16.1dev,>=16.0dev
Requires-Dist: odoo<16.1dev,>=16.0a
Requires-Dist: requests
Requires-Dist: typesense>=1.1.0
